eat/VERSION
eat/__init__.py
eat/runeat.py
eat/runtests.py
eat/beam_algorithm/__init__.py
eat/beam_algorithm/beam.py
eat/core/__init__.py
eat/core/components.py
eat/core/utilities.py
eat/deep_drilling_algorithm/__init__.py
eat/deep_drilling_algorithm/dda.py
eat/utilities/__init__.py
eat/utilities/argparse_types.py
evolution_of_algebraic_terms-2.2.6.dist-info/licenses/LICENSE
evolution_of_algebraic_terms-2.2.6.dist-info/METADATA
evolution_of_algebraic_terms-2.2.6.dist-info/WHEEL
evolution_of_algebraic_terms-2.2.6.dist-info/entry_points.txt
evolution_of_algebraic_terms-2.2.6.dist-info/top_level.txt
evolution_of_algebraic_terms-2.2.6.dist-info/RECORD
