Metadata-Version: 2.4
Name: evolution_of_algebraic_terms
Version: 2.2.6
Summary: EAT is software implementation of the algorithms described in the paper Evolution of Algebraic Terms 4: Biological Beam Algorithms.
Home-page: https://github.com/nick-falco/eat
Author: Nicholas Falco, David M. Clark
Author-email: ncfalco@gmail.com
License: Apache License, Version 2.0
Keywords: evolutionary-computation genetics ternary-descriminator idemprimality groupoid machine-learning artifical-intellegence ai
Classifier: Intended Audience :: Developers
Classifier: License :: OSI Approved :: Apache Software License
Classifier: Operating System :: OS Independent
Classifier: Programming Language :: Python
Classifier: Programming Language :: Python :: 3.8
License-File: LICENSE
Dynamic: author
Dynamic: author-email
Dynamic: classifier
Dynamic: description
Dynamic: home-page
Dynamic: keywords
Dynamic: license
Dynamic: license-file
Dynamic: summary
